AutoTransferMachine/__init__.py
AutoTransferMachine/main.py
AutoTransferMachine/utils/__init__.py
AutoTransferMachine/utils/edittorrent/__init__.py
AutoTransferMachine/utils/edittorrent/edittorrent.py
AutoTransferMachine/utils/getinfo/__init__.py
AutoTransferMachine/utils/getinfo/info_transfer.py
AutoTransferMachine/utils/getinfo/makeyaml.py
AutoTransferMachine/utils/getinfo/torrent_download.py
AutoTransferMachine/utils/img_upload/__init__.py
AutoTransferMachine/utils/img_upload/chevereto.py
AutoTransferMachine/utils/img_upload/imgbox.py
AutoTransferMachine/utils/img_upload/imgupload.py
AutoTransferMachine/utils/img_upload/ptpimg.py
AutoTransferMachine/utils/img_upload/smms.py
AutoTransferMachine/utils/mediafile/__init__.py
AutoTransferMachine/utils/mediafile/douban_book.py
AutoTransferMachine/utils/mediafile/douban_movie.py
AutoTransferMachine/utils/mediafile/doubaninfo.py
AutoTransferMachine/utils/mediafile/maketorrent.py
AutoTransferMachine/utils/mediafile/mediafile.py
AutoTransferMachine/utils/para_ctrl/__init__.py
AutoTransferMachine/utils/para_ctrl/para_ctrl.py
AutoTransferMachine/utils/para_ctrl/readargs.py
AutoTransferMachine/utils/para_ctrl/readyaml.py
AutoTransferMachine/utils/pathinfo/__init__.py
AutoTransferMachine/utils/pathinfo/pathinfo.py
AutoTransferMachine/utils/seed_machine/__init__.py
AutoTransferMachine/utils/seed_machine/qb_control.py
AutoTransferMachine/utils/seed_machine/seed_machine.py
AutoTransferMachine/utils/site/__init__.py
AutoTransferMachine/utils/site/site.py
AutoTransferMachine/utils/uploader/__init__.py
AutoTransferMachine/utils/uploader/audience_upload.py
AutoTransferMachine/utils/uploader/auto_upload.py
AutoTransferMachine/utils/uploader/btschool_upload.py
AutoTransferMachine/utils/uploader/carpt_upload.py
AutoTransferMachine/utils/uploader/cyanbug_upload.py
AutoTransferMachine/utils/uploader/dajiao_upload.py
AutoTransferMachine/utils/uploader/discfan_upload.py
AutoTransferMachine/utils/uploader/dragonhd_upload.py
AutoTransferMachine-0.0.4.dist-info/METADATA
AutoTransferMachine-0.0.4.dist-info/WHEEL
AutoTransferMachine-0.0.4.dist-info/top_level.txt
AutoTransferMachine-0.0.4.dist-info/RECORD
